info/gianlucacosta/wikiprism/__init__.py
info/gianlucacosta/wikiprism/dictionary/__init__.py
info/gianlucacosta/wikiprism/dictionary/memory.py
info/gianlucacosta/wikiprism/dictionary/sqlite.py
info/gianlucacosta/wikiprism/page/__init__.py
info/gianlucacosta/wikiprism/page/sax.py
info/gianlucacosta/wikiprism/pipeline/__init__.py
info/gianlucacosta/wikiprism/pipeline/dictionary.py
info/gianlucacosta/wikiprism/pipeline/pool.py
info/gianlucacosta/wikiprism/pipeline/protocol.py
info/gianlucacosta/wikiprism/pipeline/sax.py
info/gianlucacosta/wikiprism/pipeline/sqlite.py
info/gianlucacosta/wikiprism/pipeline/strategy.py
info/gianlucacosta/wikiprism/pipeline/supervisor.py
info/gianlucacosta/wikiprism/py.typed
info.gianlucacosta.wikiprism-1.0.0.dist-info/LICENSE
info.gianlucacosta.wikiprism-1.0.0.dist-info/WHEEL
info.gianlucacosta.wikiprism-1.0.0.dist-info/METADATA
info.gianlucacosta.wikiprism-1.0.0.dist-info/RECORD
