Metadata-Version: 2.1
Name: info.gianlucacosta.wikiprism
Version: 1.0.0
Summary: Parse wiki pages and create dictionaries, fast, with Python
Home-page: https://github.com/giancosta86/WikiPrism
License: MIT
Keywords: library,extract,wiki,pages,dictionary,terms,pipeline
Author: Gianluca Costa
Author-email: gianluca@gianlucacosta.info
Requires-Python: >=3.10,<4.0
Classifier: Development Status :: 5 - Production/Stable
Classifier: Intended Audience :: Developers
Classifier: License :: OSI Approved :: MIT License
Classifier: Operating System :: OS Independent
Classifier: Programming Language :: Python
Classifier: Programming Language :: Python :: 3
Classifier: Programming Language :: Python :: 3.10
Classifier: Topic :: Text Processing :: Linguistic
Requires-Dist: info.gianlucacosta.eos.core (>=1.0.0,<2.0.0)
Project-URL: Documentation, https://github.com/giancosta86/WikiPrism
Project-URL: Repository, https://github.com/giancosta86/WikiPrism
